{
  "utter_dementia_patient_hallucinations": {
    "precision": 1.0,
    "recall": 1.0,
    "f1-score": 1.0,
    "support": 1
  },
  "utter_what_can_you_do": {
    "precision": 1.0,
    "recall": 1.0,
    "f1-score": 1.0,
    "support": 1
  },
  "utter_caregiver_dealing_with_guilt": {
    "precision": 1.0,
    "recall": 1.0,
    "f1-score": 1.0,
    "support": 1
  },
  "utter_dementia_nursing_home_decision": {
    "precision": 1.0,
    "recall": 1.0,
    "f1-score": 1.0,
    "support": 1
  },
  "utter_dementia_patient_pain_management": {
    "precision": 1.0,
    "recall": 1.0,
    "f1-score": 1.0,
    "support": 1
  },
  "utter_caregiver_patient_interaction": {
    "precision": 1.0,
    "recall": 1.0,
    "f1-score": 1.0,
    "support": 1
  },
  "utter_dementia_early_signs": {
    "precision": 1.0,
    "recall": 1.0,
    "f1-score": 1.0,
    "support": 1
  },
  "utter_dementia_sundowning_management": {
    "precision": 1.0,
    "recall": 1.0,
    "f1-score": 1.0,
    "support": 1
  },
  "utter_dementia_prevention_methods": {
    "precision": 1.0,
    "recall": 1.0,
    "f1-score": 1.0,
    "support": 1
  },
  "utter_dementia_misconceptions": {
    "precision": 1.0,
    "recall": 1.0,
    "f1-score": 1.0,
    "support": 1
  },
  "utter_dementia_patient_repetitive_questions": {
    "precision": 1.0,
    "recall": 1.0,
    "f1-score": 1.0,
    "support": 1
  },
  "utter_dementia_patient_eating_habits": {
    "precision": 1.0,
    "recall": 1.0,
    "f1-score": 1.0,
    "support": 1
  },
  "utter_dementia_patient_late_stage_care": {
    "precision": 1.0,
    "recall": 1.0,
    "f1-score": 1.0,
    "support": 1
  },
  "utter_dementia_patient_wandering": {
    "precision": 1.0,
    "recall": 1.0,
    "f1-score": 1.0,
    "support": 1
  },
  "utter_dementia_patient_difficulty_swallowing": {
    "precision": 1.0,
    "recall": 1.0,
    "f1-score": 1.0,
    "support": 1
  },
  "utter_dementia_patient_communication_issues": {
    "precision": 1.0,
    "recall": 1.0,
    "f1-score": 1.0,
    "support": 1
  },
  "utter_dementia_patient_hyperorality": {
    "precision": 1.0,
    "recall": 1.0,
    "f1-score": 1.0,
    "support": 1
  },
  "utter_caregiver_stress_management": {
    "precision": 1.0,
    "recall": 1.0,
    "f1-score": 1.0,
    "support": 1
  },
  "utter_dementia_patient_personality_changes": {
    "precision": 1.0,
    "recall": 1.0,
    "f1-score": 1.0,
    "support": 1
  },
  "utter_dementia_patient_hiding_objects": {
    "precision": 1.0,
    "recall": 1.0,
    "f1-score": 1.0,
    "support": 1
  },
  "utter_dementia_patient_reminiscence_therapy": {
    "precision": 1.0,
    "recall": 1.0,
    "f1-score": 1.0,
    "support": 1
  },
  "utter_dementia_patient_social_withdrawal": {
    "precision": 1.0,
    "recall": 1.0,
    "f1-score": 1.0,
    "support": 1
  },
  "utter_dementia_patient_excessive_repetitive_movements": {
    "precision": 1.0,
    "recall": 1.0,
    "f1-score": 1.0,
    "support": 1
  },
  "utter_caregiver_setting_up_routines_for_dementia_patient": {
    "precision": 1.0,
    "recall": 1.0,
    "f1-score": 1.0,
    "support": 1
  },
  "action_list_weekly_reports": {
    "precision": 1.0,
    "recall": 1.0,
    "f1-score": 1.0,
    "support": 1
  },
  "utter_dementia_patient_fidgeting": {
    "precision": 1.0,
    "recall": 1.0,
    "f1-score": 1.0,
    "support": 1
  },
  "utter_how_are_you": {
    "precision": 1.0,
    "recall": 1.0,
    "f1-score": 1.0,
    "support": 1
  },
  "utter_dementia_impact_of_diet": {
    "precision": 1.0,
    "recall": 1.0,
    "f1-score": 1.0,
    "support": 1
  },
  "utter_goodbye": {
    "precision": 1.0,
    "recall": 1.0,
    "f1-score": 1.0,
    "support": 1
  },
  "utter_dementia_statistics": {
    "precision": 1.0,
    "recall": 1.0,
    "f1-score": 1.0,
    "support": 1
  },
  "utter_dementia_patient_sleep_cycle_disruption": {
    "precision": 1.0,
    "recall": 1.0,
    "f1-score": 1.0,
    "support": 1
  },
  "utter_caregiver_effect_on_mental_health": {
    "precision": 1.0,
    "recall": 1.0,
    "f1-score": 1.0,
    "support": 1
  },
  "utter_dementia_brain_exercises": {
    "precision": 1.0,
    "recall": 1.0,
    "f1-score": 1.0,
    "support": 1
  },
  "utter_dementia_patient_aggression": {
    "precision": 1.0,
    "recall": 1.0,
    "f1-score": 1.0,
    "support": 1
  },
  "action_listen": {
    "precision": 1.0,
    "recall": 1.0,
    "f1-score": 1.0,
    "support": 92
  },
  "utter_dementia_patient_loss_of_interest": {
    "precision": 1.0,
    "recall": 1.0,
    "f1-score": 1.0,
    "support": 1
  },
  "utter_dementia_palliative_care": {
    "precision": 1.0,
    "recall": 1.0,
    "f1-score": 1.0,
    "support": 1
  },
  "utter_chatbot_skip_question": {
    "precision": 1.0,
    "recall": 1.0,
    "f1-score": 1.0,
    "support": 1
  },
  "utter_dementia_treatment_medical": {
    "precision": 1.0,
    "recall": 1.0,
    "f1-score": 1.0,
    "support": 1
  },
  "utter_caregiver_setting_boundaries": {
    "precision": 1.0,
    "recall": 1.0,
    "f1-score": 1.0,
    "support": 1
  },
  "utter_dementia_symptoms": {
    "precision": 1.0,
    "recall": 1.0,
    "f1-score": 1.0,
    "support": 1
  },
  "utter_dementia_patient_sensitivity_to_noise": {
    "precision": 1.0,
    "recall": 1.0,
    "f1-score": 1.0,
    "support": 1
  },
  "utter_dementia_patient_not_recognizing_home": {
    "precision": 1.0,
    "recall": 1.0,
    "f1-score": 1.0,
    "support": 1
  },
  "utter_dementia_technology_assistance": {
    "precision": 1.0,
    "recall": 1.0,
    "f1-score": 1.0,
    "support": 1
  },
  "utter_dementia_types": {
    "precision": 1.0,
    "recall": 1.0,
    "f1-score": 1.0,
    "support": 1
  },
  "utter_dementia_patient_sleep_issues": {
    "precision": 1.0,
    "recall": 1.0,
    "f1-score": 1.0,
    "support": 1
  },
  "utter_dementia_patient_wandering_outside": {
    "precision": 1.0,
    "recall": 1.0,
    "f1-score": 1.0,
    "support": 1
  },
  "utter_caregiver_time_management": {
    "precision": 1.0,
    "recall": 1.0,
    "f1-score": 1.0,
    "support": 1
  },
  "utter_chatbot_rephrase_answer": {
    "precision": 1.0,
    "recall": 1.0,
    "f1-score": 1.0,
    "support": 1
  },
  "utter_dementia_patient_resisting_help": {
    "precision": 1.0,
    "recall": 1.0,
    "f1-score": 1.0,
    "support": 1
  },
  "utter_caregiver_long_distance_care": {
    "precision": 1.0,
    "recall": 1.0,
    "f1-score": 1.0,
    "support": 1
  },
  "utter_caregiver_tips": {
    "precision": 1.0,
    "recall": 1.0,
    "f1-score": 1.0,
    "support": 1
  },
  "utter_dementia_patient_legal_rights": {
    "precision": 1.0,
    "recall": 1.0,
    "f1-score": 1.0,
    "support": 1
  },
  "utter_thank_you": {
    "precision": 1.0,
    "recall": 1.0,
    "f1-score": 1.0,
    "support": 1
  },
  "utter_caregiver_understanding_dementia_patient_emotions": {
    "precision": 1.0,
    "recall": 1.0,
    "f1-score": 1.0,
    "support": 1
  },
  "utter_dementia_patient_wandering_prevention": {
    "precision": 1.0,
    "recall": 1.0,
    "f1-score": 1.0,
    "support": 1
  },
  "utter_dementia_vs_normal_aging": {
    "precision": 1.0,
    "recall": 1.0,
    "f1-score": 1.0,
    "support": 1
  },
  "utter_group_made_me": {
    "precision": 1.0,
    "recall": 1.0,
    "f1-score": 1.0,
    "support": 1
  },
  "utter_caregiver_helping_dementia_patient_make_decisions": {
    "precision": 1.0,
    "recall": 1.0,
    "f1-score": 1.0,
    "support": 1
  },
  "utter_caregiver_how_to_handle_dementia_patient_refusing_medication": {
    "precision": 1.0,
    "recall": 1.0,
    "f1-score": 1.0,
    "support": 1
  },
  "utter_caregiver_sibling_disagreements": {
    "precision": 1.0,
    "recall": 1.0,
    "f1-score": 1.0,
    "support": 1
  },
  "utter_greet": {
    "precision": 1.0,
    "recall": 1.0,
    "f1-score": 1.0,
    "support": 1
  },
  "utter_dementia_hospice_care": {
    "precision": 1.0,
    "recall": 1.0,
    "f1-score": 1.0,
    "support": 1
  },
  "utter_dementia_patient_dressing_difficulties": {
    "precision": 1.0,
    "recall": 1.0,
    "f1-score": 1.0,
    "support": 1
  },
  "utter_dementia_treatment_lifestyle": {
    "precision": 1.0,
    "recall": 1.0,
    "f1-score": 1.0,
    "support": 1
  },
  "utter_dementia_friendly_home_tips": {
    "precision": 1.0,
    "recall": 1.0,
    "f1-score": 1.0,
    "support": 1
  },
  "utter_dementia_patient_personal_recognition_loss": {
    "precision": 1.0,
    "recall": 1.0,
    "f1-score": 1.0,
    "support": 1
  },
  "utter_dementia_patient_aggression_management": {
    "precision": 1.0,
    "recall": 1.0,
    "f1-score": 1.0,
    "support": 1
  },
  "utter_caregiver_dementia_patient_denial": {
    "precision": 1.0,
    "recall": 1.0,
    "f1-score": 1.0,
    "support": 1
  },
  "utter_dementia_definition": {
    "precision": 1.0,
    "recall": 1.0,
    "f1-score": 1.0,
    "support": 1
  },
  "utter_dementia_patient_speech_changes": {
    "precision": 1.0,
    "recall": 1.0,
    "f1-score": 1.0,
    "support": 1
  },
  "utter_dementia_diagnosis_prevention": {
    "precision": 1.0,
    "recall": 1.0,
    "f1-score": 1.0,
    "support": 1
  },
  "utter_dementia_patient_shadowing_behavior": {
    "precision": 1.0,
    "recall": 1.0,
    "f1-score": 1.0,
    "support": 1
  },
  "action_provide_selected_report": {
    "precision": 1.0,
    "recall": 1.0,
    "f1-score": 1.0,
    "support": 1
  },
  "utter_caregiver_managing_dementia_patient_social_isolation": {
    "precision": 1.0,
    "recall": 1.0,
    "f1-score": 1.0,
    "support": 1
  },
  "utter_dementia_assistive_devices": {
    "precision": 1.0,
    "recall": 1.0,
    "f1-score": 1.0,
    "support": 1
  },
  "utter_dementia_support_services": {
    "precision": 1.0,
    "recall": 1.0,
    "f1-score": 1.0,
    "support": 1
  },
  "utter_dementia_patient_emotional_changes": {
    "precision": 1.0,
    "recall": 1.0,
    "f1-score": 1.0,
    "support": 1
  },
  "utter_caregiver_support_for_family_members": {
    "precision": 1.0,
    "recall": 1.0,
    "f1-score": 1.0,
    "support": 1
  },
  "utter_dementia_patient_daily_routines": {
    "precision": 1.0,
    "recall": 1.0,
    "f1-score": 1.0,
    "support": 1
  },
  "utter_dementia_patient_hygiene_care": {
    "precision": 1.0,
    "recall": 1.0,
    "f1-score": 1.0,
    "support": 1
  },
  "utter_dementia_causes": {
    "precision": 1.0,
    "recall": 1.0,
    "f1-score": 1.0,
    "support": 1
  },
  "utter_dementia_patient_physical_disability": {
    "precision": 1.0,
    "recall": 1.0,
    "f1-score": 1.0,
    "support": 1
  },
  "utter_dementia_patient_resistance_to_change": {
    "precision": 1.0,
    "recall": 1.0,
    "f1-score": 1.0,
    "support": 1
  },
  "utter_dementia_patient_lack_of_awareness": {
    "precision": 1.0,
    "recall": 1.0,
    "f1-score": 1.0,
    "support": 1
  },
  "utter_dementia_patient_fixation_on_past_events": {
    "precision": 1.0,
    "recall": 1.0,
    "f1-score": 1.0,
    "support": 1
  },
  "utter_dementia_patient_paranoia": {
    "precision": 1.0,
    "recall": 1.0,
    "f1-score": 1.0,
    "support": 1
  },
  "utter_dementia_patient_fear_and_anxiety": {
    "precision": 1.0,
    "recall": 1.0,
    "f1-score": 1.0,
    "support": 1
  },
  "utter_dementia_risk_factors": {
    "precision": 1.0,
    "recall": 1.0,
    "f1-score": 1.0,
    "support": 1
  },
  "utter_dementia_patient_confusion": {
    "precision": 1.0,
    "recall": 1.0,
    "f1-score": 1.0,
    "support": 1
  },
  "utter_caregiver_burnout_prevention": {
    "precision": 1.0,
    "recall": 1.0,
    "f1-score": 1.0,
    "support": 1
  },
  "utter_dementia_patient_loss_of_time_awareness": {
    "precision": 1.0,
    "recall": 1.0,
    "f1-score": 1.0,
    "support": 1
  },
  "utter_dementia_transportation_challenges": {
    "precision": 1.0,
    "recall": 1.0,
    "f1-score": 1.0,
    "support": 1
  },
  "accuracy": 1.0,
  "macro avg": {
    "precision": 1.0,
    "recall": 1.0,
    "f1-score": 1.0,
    "support": 184
  },
  "weighted avg": {
    "precision": 1.0,
    "recall": 1.0,
    "f1-score": 1.0,
    "support": 184
  },
  "micro avg": {
    "precision": 1.0,
    "recall": 1.0,
    "f1-score": 1.0,
    "support": 184
  },
  "conversation_accuracy": {
    "accuracy": 1.0,
    "correct": 91,
    "with_warnings": 0,
    "total": 91
  }
}